{"tinyType":"alipay","tinyCnName":"支付宝","tinyProjectType":"alipay-mini","alipay:alipay-mini:tinyIcon":null,"alipay:alipay-mini:auditLink":null,"alipay:alipay-mini:whiteListLink":null,"alipay:alipay-mini:createLink":null,"alipay:alipay-mini:projectUserId":"2088312833799940","alipay:alipay-mini:appId":"2019070865734911","alipay:alipay-mini:appName":"Loopoo","alipay:alipay-mini:orgId":null,"alipay:alipay-mini:corpId":null,"alipay:alipay-mini:remoteVersion":"0.0.6","alipay:alipay-mini:currentVersion":"0.0.7","alipay:alipay-mini:whiteList":["api.map.baidu.com","test-wap.juewei.com","imgcdnjwd.juewei.com"],"alipay:alipay-mini:h5WhiteList":["test-wap.juewei.com"],"alipay:alipay-mini:appLogo":"https://appstoreisvpic.alipayobjects.com/prod/f3b5a4c9-579b-493f-93b9-6b8a73085dcf.png","alipay:alipay-mini:stopRefresh":false,"SimulatorMode":"EMBED","isSimulatorOpen":true,"isSimulatorDefaultSticky":false,"isNotFirstToggleSimulator":true,"alipay:alipay-mini:locationAuth":true}
